magic/__init__.py
magic/__main__.py
magic/deployment/__init__.py
magic/deployment/deploy.py
magic/deployment/remote_manager.py
magic/deployment/rsync.py
magic/deployment/sftp_client.py
magic/deployment/sftp_get.py
magic/deployment/sftp_put.py
magic/deployment/ssh_login.py
magic/scripts/__init__.py
magic/scripts/check_cc_code_style.py
magic/scripts/force_kill.sh
magic/scripts/shell_wrapper.py
magic/video_utils/__init__.py
magic/video_utils/image2video.py
magic/video_utils/record_video.py
magic_toolkit-1.3.0.dist-info/LICENSE
magic_toolkit-1.3.0.dist-info/METADATA
magic_toolkit-1.3.0.dist-info/WHEEL
magic_toolkit-1.3.0.dist-info/entry_points.txt
magic_toolkit-1.3.0.dist-info/top_level.txt
magic_toolkit-1.3.0.dist-info/RECORD
